setup.cfg
setup.py
auto_provider.egg-info/PKG-INFO
auto_provider.egg-info/SOURCES.txt
auto_provider.egg-info/dependency_links.txt
auto_provider.egg-info/entry_points.txt
auto_provider.egg-info/not-zip-safe
auto_provider.egg-info/requires.txt
auto_provider.egg-info/top_level.txt
provider/__init__.py
provider/cli.py
provider/config.py
provider/provider_ios.py
provider/provider_win.py