Metadata-Version: 1.1
Name: auto-provider
Version: 0.0.5
Summary: device provider for automation test.
Home-page: https://github.com/hustcc
Author: hustcc
Author-email: i@hust.cc
License: GPL
Keywords: device,provider
Platform: UNKNOWN
Classifier: Intended Audience :: Developers
Classifier: Operating System :: OS Independent
Classifier: Natural Language :: Chinese (Simplified)
Classifier: Programming Language :: Python
Classifier: Programming Language :: Python :: 2
Classifier: Programming Language :: Python :: 2.5
Classifier: Programming Language :: Python :: 2.6
Classifier: Programming Language :: Python :: 2.7
Classifier: Topic :: Utilities
